odoo9_addon_account_payment_term_extension-9.0.1.0.0.99.dev14-py2.7-nspkg.pth
odoo9_addon_account_payment_term_extension-9.0.1.0.0.99.dev14.dist-info/METADATA
odoo9_addon_account_payment_term_extension-9.0.1.0.0.99.dev14.dist-info/RECORD
odoo9_addon_account_payment_term_extension-9.0.1.0.0.99.dev14.dist-info/WHEEL
odoo9_addon_account_payment_term_extension-9.0.1.0.0.99.dev14.dist-info/namespace_packages.txt
odoo9_addon_account_payment_term_extension-9.0.1.0.0.99.dev14.dist-info/top_level.txt
odoo_addons/account_payment_term_extension/README.rst
odoo_addons/account_payment_term_extension/__init__.py
odoo_addons/account_payment_term_extension/__openerp__.py
odoo_addons/account_payment_term_extension/account.py
odoo_addons/account_payment_term_extension/account_demo.xml
odoo_addons/account_payment_term_extension/account_view.xml
odoo_addons/account_payment_term_extension/documentation/DOC_payment_terms_rounding.ods
odoo_addons/account_payment_term_extension/i18n/account_payment_term_extension.pot
odoo_addons/account_payment_term_extension/i18n/de.po
odoo_addons/account_payment_term_extension/i18n/es.po
odoo_addons/account_payment_term_extension/i18n/fr.po
odoo_addons/account_payment_term_extension/i18n/hr_HR.po
odoo_addons/account_payment_term_extension/i18n/nl_NL.po
odoo_addons/account_payment_term_extension/i18n/pt_BR.po
odoo_addons/account_payment_term_extension/i18n/sl.po
odoo_addons/account_payment_term_extension/i18n/tr_TR.po
odoo_addons/account_payment_term_extension/static/description/icon.png
odoo_addons/account_payment_term_extension/static/description/icon.svg
odoo_addons/account_payment_term_extension/static/description/payment_term_form.jpg
odoo_addons/account_payment_term_extension/tests/__init__.py
odoo_addons/account_payment_term_extension/tests/test_account_payment_term_multi_day.py
odoo_addons/account_payment_term_extension/tests/test_payment_term.py
